pyhackrf2_htime/__init__.py
pyhackrf2_htime/cinterface.py
pyhackrf2_htime-1.0.3.dist-info/COPYING
pyhackrf2_htime-1.0.3.dist-info/METADATA
pyhackrf2_htime-1.0.3.dist-info/WHEEL
pyhackrf2_htime-1.0.3.dist-info/top_level.txt
pyhackrf2_htime-1.0.3.dist-info/RECORD
