Metadata-Version: 2.2
Name: pyhackrf2_htime
Version: 1.0.3
Summary: Python bindings for libhackrf rewritten plus HTime extension
Classifier: Topic :: Communications :: Ham Radio
Classifier: License :: OSI Approved :: MIT License
Classifier: Operating System :: OS Independent
Requires-Python: >=3
License-File: COPYING
Requires-Dist: numpy>=1.24
